__init__.py
sas.py
mas_test/la/__init__.py
mas_test/la/las.py
mas_test/python/eksamen/1t/2022_h/del_1/03/oppg_3_a_rasjonal_funksjon_bug.py
mas_test/python/eksamen/1t/2022_h/del_1/03/oppg_3_b_rasjonal_funksjon_if.py
mas_test/python/eksamen/1t/2022_h/del_1/03/oppg_3_b_rasjonal_funksjon_if_else.py
mas_test/python/eksamen/1t/2022_v/del_1/04/oppg_4_kvadrattall.py
mas_test/python/eksamen/s1/2023_h/del_1/05/oppg_5_grensekostnad.py
mas_test/python/eksamen/s1/2023_h/del_2/01/01_oppg_1_a_1_sofa_mas.py
mas_test/python/eksamen/s1/2023_h/del_2/01/01_oppg_1_a_2_sofa_def_reggis_str_mas.py
mas_test/python/eksamen/s1/2023_h/del_2/01/01_oppg_1_a_3_sofa_def_reggis_cas_mas.py
mas_test/python/eksamen/s1/2023_h/del_2/01/01_oppg_1_a_4_sofa_matematikk_mas.py
mas_test/python/eksamen/s1/2023_h/del_2/01/01_oppg_1_a_5_sofa_matematikk_speedrun_mas.py
mas_test/python/eksamen/s1/2023_h/del_2/01/01_oppg_1_b_1_sofa_mas.py
mas_test/python/eksamen/s1/2023_h/del_2/01/01_oppg_1_b_2_sofa_def_superlos_mas.py
mas_test/python/eksamen/s1/2023_h/del_2/01/01_oppg_1_b_3_sofa_matematikk_mas.py
mas_test/python/eksamen/s1/2023_h/del_2/01/01_oppg_1_b_4_sofa_def_overskudd_max_mas.py
mas_test/python/eksamen/s1/2023_h/del_2/01/01_oppg_1_b_5_sofa_abstrahering_mas.py
mas_test/python/eksamen/s1/2023_h/del_2/01/01_oppg_1_b_6_sofa_matematikk_mas.py
mas_test/python/eksamen/s1/2023_h/del_2/01/01_oppg_1_b_7_sofa_matematikk_speedrun_mas.py
mas_test/python/eksamen/s1/2023_h/del_2/01/01_oppg_1_c_sofa_mas.py
mas_test/python/eksamen/s1/2023_h/del_2/01/02_oppg_1_a_sofa_torodd.py
mas_test/python/eksamen/s1/2023_h/del_2/01/02_oppg_1_b_sofa_torodd.py
mas_test/python/eksamen/s1/2023_h/del_2/01/02_oppg_1_c_sofa_torodd.py
mas_test/python/eksamen/s1/2023_h/del_2/02/01_oppg_2_a_venstrehendte_mas.py
mas_test/python/eksamen/s1/2023_h/del_2/02/01_oppg_2_b_1_venstrehendte_mas.py
mas_test/python/eksamen/s1/2023_h/del_2/02/01_oppg_2_b_2_venstrehendte_relasjoner_mas.py
mas_test/python/eksamen/s1/2023_h/del_2/02/01_oppg_2_c_venstrehendte_mas.py
mas_test-0.0.13.dist-info/LICENCE
mas_test-0.0.13.dist-info/METADATA
mas_test-0.0.13.dist-info/WHEEL
mas_test-0.0.13.dist-info/top_level.txt
mas_test-0.0.13.dist-info/RECORD
